pathwaysutils/__init__.py
pathwaysutils/_initialize.py
pathwaysutils/collect_profile.py
pathwaysutils/lru_cache.py
pathwaysutils/plugin_executable.py
pathwaysutils/profiling.py
pathwaysutils/proxy_backend.py
pathwaysutils/debug/__init__.py
pathwaysutils/debug/timing.py
pathwaysutils/debug/watchdog.py
pathwaysutils/elastic/__init__.py
pathwaysutils/elastic/manager.py
pathwaysutils/elastic/reshard.py
pathwaysutils/elastic/simulated_manager.py
pathwaysutils/experimental/__init__.py
pathwaysutils/experimental/reshard.py
pathwaysutils/experimental/split_by_mesh_axis.py
pathwaysutils/jax/__init__.py
pathwaysutils/persistence/__init__.py
pathwaysutils/persistence/helper.py
pathwaysutils/persistence/orbax_handler.py
pathwaysutils/sidecar/README.md
pathwaysutils/sidecar/python/Dockerfile
pathwaysutils/sidecar/python/requirements.txt
pathwaysutils-0.1.3.dist-info/entry_points.txt
pathwaysutils-0.1.3.dist-info/licenses/LICENSE
pathwaysutils-0.1.3.dist-info/WHEEL
pathwaysutils-0.1.3.dist-info/METADATA
pathwaysutils-0.1.3.dist-info/RECORD
