Metadata-Version: 2.4
Name: pathwaysutils
Version: 0.1.3
Summary: Package of Pathways-on-Cloud utilities.
Keywords: 
Author-email: Pathways-on-Cloud Utilities Developers <pathwaysutils-dev@google.com>
Requires-Python: >=3.10
Classifier: License :: OSI Approved :: Apache Software License
License-File: LICENSE
Requires-Dist: absl-py
Requires-Dist: fastapi
Requires-Dist: jax>=0.4.26
Requires-Dist: orbax-checkpoint
Requires-Dist: uvicorn
Requires-Dist: requests
Requires-Dist: pylint>=2.6.0 ; extra == "dev"
Requires-Dist: pyink ; extra == "dev"
Project-URL: changelog, https://github.com/AI-Hypercomputer/pathways-utils/blob/main/CHANGELOG.md
Project-URL: homepage, https://github.com/AI-Hypercomputer/pathways-utils
Project-URL: repository, https://github.com/AI-Hypercomputer/pathways-utils
Provides-Extra: dev
